sdtk/__init__.py
sdtk/sdtk.py
sdtk_visllc-0.2.3.dist-info/LICENSE
sdtk_visllc-0.2.3.dist-info/METADATA
sdtk_visllc-0.2.3.dist-info/WHEEL
sdtk_visllc-0.2.3.dist-info/top_level.txt
sdtk_visllc-0.2.3.dist-info/RECORD
