Metadata-Version: 2.1
Name: sdtk-visllc
Version: 0.2.3
Summary: Simple Data Toolkit - Manipulate CSV, TSV, PSV and other data formats
Home-page: https://vis-software.com/#sdtk
Author: Vis LLC
Author-email: info@vis-software.com
Project-URL: Bug Tracker, https://github.com/Vis-LLC/Simple-Data-Toolkit/issues
Classifier: Programming Language :: Other
Classifier: License :: OSI Approved :: GNU Lesser General Public License v3 (LGPLv3)
Classifier: Operating System :: OS Independent
License-File: LICENSE
